subtractor/__init__.py
subtractor/__main__.py
subtractor/cli.py
subtractor/pixel.py
subtractor/report.py
subtractor/stream.py
subtractor/subtractor.py
subtractor-2023.10.21.dist-info/LICENSE
subtractor-2023.10.21.dist-info/METADATA
subtractor-2023.10.21.dist-info/WHEEL
subtractor-2023.10.21.dist-info/entry_points.txt
subtractor-2023.10.21.dist-info/top_level.txt
subtractor-2023.10.21.dist-info/RECORD
